crackle_automation_api_client/__init__.py
crackle_automation_api_client/api_wrapper.py
crackle_automation_api_client/missing_credentials_error.py
crackle_automation_api_client/session.py
crackle_automation_api_client/tests.py
crackle_automation_api_client-0.3.dist-info/METADATA
crackle_automation_api_client-0.3.dist-info/WHEEL
crackle_automation_api_client-0.3.dist-info/top_level.txt
crackle_automation_api_client-0.3.dist-info/zip-safe
crackle_automation_api_client-0.3.dist-info/RECORD
