Metadata-Version: 2.1
Name: crackle-automation-api-client
Version: 0.3
Summary: Python API Wrapper for Crackle Automation Reporter Web Service
Home-page: UNKNOWN
Author: Clark Mckenzie
Author-email: clarkmckenzie@gmail.com
License: No License
Platform: UNKNOWN
Requires-Dist: requests
